pyproject2spack/__init__.py
pyproject2spack/package.py
pyproject2spack/pyproject2spack.py
pyproject2spack/spackdb.json
pyproject2spack/logger/__init__.py
pyproject2spack/logger/logger.py
pyproject2spack/matcher/__init__.py
pyproject2spack/matcher/spack.py
pyproject2spack/parser/__init__.py
pyproject2spack/parser/pyproject.py
pyproject2spack/renderer/__init__.py
pyproject2spack/renderer/jinja2.py
pyproject2spack/templates/package.py.j2
pyproject2spack-1.5.0.dist-info/LICENSE
pyproject2spack-1.5.0.dist-info/METADATA
pyproject2spack-1.5.0.dist-info/WHEEL
pyproject2spack-1.5.0.dist-info/entry_points.txt
pyproject2spack-1.5.0.dist-info/top_level.txt
pyproject2spack-1.5.0.dist-info/RECORD
